seissolxdmfwriter/__init__.py
seissolxdmfwriter/seissol_output_extractor.py
seissolxdmfwriter/seissolxdmfwriter.py
seissolxdmfwriter-0.4.4.dist-info/licenses/LICENSE
seissolxdmfwriter-0.4.4.dist-info/METADATA
seissolxdmfwriter-0.4.4.dist-info/WHEEL
seissolxdmfwriter-0.4.4.dist-info/entry_points.txt
seissolxdmfwriter-0.4.4.dist-info/top_level.txt
seissolxdmfwriter-0.4.4.dist-info/RECORD
