Metadata-Version: 2.4
Name: seissolxdmfwriter
Version: 0.4.4
Summary: A python writer for SeisSol xdmf output
Author: SeisSol Group
Project-URL: Repository, https://github.com/SeisSol/Visualization/seissolxdmfwriter
Keywords: SeisSol
Classifier: Programming Language :: Python :: 3
Classifier: Operating System :: OS Independent
Requires-Python: >=3.6
License-File: LICENSE
Requires-Dist: numpy
Requires-Dist: h5py
Requires-Dist: seissolxdmf>=0.1.2
Requires-Dist: tqdm
Dynamic: license-file
